thinking_processes/__init__.py
thinking_processes/diagram.py
thinking_processes/evaporating_cloud.py
thinking_processes/current_reality_tree/__init__.py
thinking_processes/current_reality_tree/causal_relation.py
thinking_processes/current_reality_tree/current_reality_tree.py
thinking_processes/current_reality_tree/node.py
thinking_processes/future_reality_tree/__init__.py
thinking_processes/future_reality_tree/causal_relation.py
thinking_processes/future_reality_tree/future_reality_tree.py
thinking_processes/future_reality_tree/node.py
thinking_processes/prerequisite_tree/__init__.py
thinking_processes/prerequisite_tree/node.py
thinking_processes/prerequisite_tree/prerequisite_tree.py
thinking_processes-1.3.1.dist-info/licenses/LICENSE
thinking_processes-1.3.1.dist-info/METADATA
thinking_processes-1.3.1.dist-info/WHEEL
thinking_processes-1.3.1.dist-info/top_level.txt
thinking_processes-1.3.1.dist-info/RECORD
