Metadata-Version: 2.4
Name: thinking-processes
Version: 1.3.1
Summary: Diagramming tools for the Thinking Processes from the Theory of Constraints
Author-email: Boris Wiegand <boris.wiegand@stahl-holding-saar.de>
License:                     GNU GENERAL PUBLIC LICENSE
Keywords: TOC,theory of constraints,current reality tree,evaporation cloud,conflict resolution diagram,thinking processes
Classifier: Intended Audience :: Education
Classifier: Intended Audience :: Manufacturing
Classifier: Intended Audience :: Science/Research
Classifier: Intended Audience :: Other Audience
Classifier: Topic :: Documentation
Classifier: Topic :: Office/Business
Classifier: License :: OSI Approved :: GNU General Public License v3 (GPLv3)
Classifier: Programming Language :: Python :: 3
Classifier: Programming Language :: Python :: 3 :: Only
Requires-Python: >=3.11
License-File: LICENSE
Requires-Dist: graphviz
Requires-Dist: drawpyo
Dynamic: license-file
